[
  {
    "aggregateAt": 1731322799000,
    "chapterEndAt": 1731323399000,
    "chapterNo": 1,
    "chapterStartAt": 1731063600000,
    "eventId": 112,
    "gameCharacterId": 18,
    "id": 11201,
    "isSupplemental": false,
    "worldBloomChapterType": "game_character"
  },
  {
    "aggregateAt": 1731581999000,
    "chapterEndAt": 1731582599000,
    "chapterNo": 2,
    "chapterStartAt": 1731322800000,
    "eventId": 112,
    "gameCharacterId": 20,
    "id": 11202,
    "isSupplemental": false,
    "worldBloomChapterType": "game_character"
  },
  {
    "aggregateAt": 1731841199000,
    "chapterEndAt": 1731841799000,
    "chapterNo": 3,
    "chapterStartAt": 1731582000000,
    "eventId": 112,
    "gameCharacterId": 19,
    "id": 11203,
    "isSupplemental": false,
    "worldBloomChapterType": "game_character"
  },
  {
    "aggregateAt": 1732100399000,
    "chapterEndAt": 1732100999000,
    "chapterNo": 4,
    "chapterStartAt": 1731841200000,
    "eventId": 112,
    "gameCharacterId": 17,
    "id": 11204,
    "isSupplemental": false,
    "worldBloomChapterType": "game_character"
  },
  {
    "aggregateAt": 1736679599000,
    "chapterEndAt": 1736680199000,
    "chapterNo": 1,
    "chapterStartAt": 1736420400000,
    "eventId": 118,
    "gameCharacterId": 11,
    "id": 11801,
    "isSupplemental": false,
    "worldBloomChapterType": "game_character"
  },
  {
    "aggregateAt": 1736938799000,
    "chapterEndAt": 1736939399000,
    "chapterNo": 2,
    "chapterStartAt": 1736679600000,
    "eventId": 118,
    "gameCharacterId": 12,
    "id": 11802,
    "isSupplemental": false,
    "worldBloomChapterType": "game_character"
  },
  {
    "aggregateAt": 1737197999000,
    "chapterEndAt": 1737198599000,
    "chapterNo": 3,
    "chapterStartAt": 1736938800000,
    "eventId": 118,
    "gameCharacterId": 10,
    "id": 11803,
    "isSupplemental": false,
    "worldBloomChapterType": "game_character"
  },
  {
    "aggregateAt": 1737457199000,
    "chapterEndAt": 1737457799000,
    "chapterNo": 4,
    "chapterStartAt": 1737198000000,
    "eventId": 118,
    "gameCharacterId": 9,
    "id": 11804,
    "isSupplemental": false,
    "worldBloomChapterType": "game_character"
  },
  {
    "aggregateAt": 1741690799000,
    "chapterEndAt": 1741691399000,
    "chapterNo": 1,
    "chapterStartAt": 1741431600000,
    "eventId": 124,
    "gameCharacterId": 16,
    "id": 12401,
    "isSupplemental": false,
    "worldBloomChapterType": "game_character"
  },
  {
    "aggregateAt": 1741949999000,
    "chapterEndAt": 1741950599000,
    "chapterNo": 2,
    "chapterStartAt": 1741690800000,
    "eventId": 124,
    "gameCharacterId": 15,
    "id": 12402,
    "isSupplemental": false,
    "worldBloomChapterType": "game_character"
  },
  {
    "aggregateAt": 1742209199000,
    "chapterEndAt": 1742209799000,
    "chapterNo": 3,
    "chapterStartAt": 1741950000000,
    "eventId": 124,
    "gameCharacterId": 14,
    "id": 12403,
    "isSupplemental": false,
    "worldBloomChapterType": "game_character"
  },
  {
    "aggregateAt": 1742468399000,
    "chapterEndAt": 1742468999000,
    "chapterNo": 4,
    "chapterStartAt": 1742209200000,
    "eventId": 124,
    "gameCharacterId": 13,
    "id": 12404,
    "isSupplemental": false,
    "worldBloomChapterType": "game_character"
  },
  {
    "aggregateAt": 1747047599000,
    "chapterEndAt": 1747048199000,
    "chapterNo": 1,
    "chapterStartAt": 1746788400000,
    "eventId": 130,
    "gameCharacterId": 7,
    "id": 13001,
    "isSupplemental": false,
    "worldBloomChapterType": "game_character"
  },
  {
    "aggregateAt": 1747306799000,
    "chapterEndAt": 1747307399000,
    "chapterNo": 2,
    "chapterStartAt": 1747047600000,
    "eventId": 130,
    "gameCharacterId": 6,
    "id": 13002,
    "isSupplemental": false,
    "worldBloomChapterType": "game_character"
  },
  {
    "aggregateAt": 1747565999000,
    "chapterEndAt": 1747566599000,
    "chapterNo": 3,
    "chapterStartAt": 1747306800000,
    "eventId": 130,
    "gameCharacterId": 8,
    "id": 13003,
    "isSupplemental": false,
    "worldBloomChapterType": "game_character"
  },
  {
    "aggregateAt": 1747825199000,
    "chapterEndAt": 1747825799000,
    "chapterNo": 4,
    "chapterStartAt": 1747566000000,
    "eventId": 130,
    "gameCharacterId": 5,
    "id": 13004,
    "isSupplemental": false,
    "worldBloomChapterType": "game_character"
  },
  {
    "aggregateAt": 1753009199000,
    "chapterEndAt": 1753009799000,
    "chapterNo": 1,
    "chapterStartAt": 1752750000000,
    "eventId": 137,
    "gameCharacterId": 2,
    "id": 13701,
    "isSupplemental": false,
    "worldBloomChapterType": "game_character"
  },
  {
    "aggregateAt": 1753268399000,
    "chapterEndAt": 1753268999000,
    "chapterNo": 2,
    "chapterStartAt": 1753009200000,
    "eventId": 137,
    "gameCharacterId": 3,
    "id": 13702,
    "isSupplemental": false,
    "worldBloomChapterType": "game_character"
  },
  {
    "aggregateAt": 1753527599000,
    "chapterEndAt": 1753528199000,
    "chapterNo": 3,
    "chapterStartAt": 1753268400000,
    "eventId": 137,
    "gameCharacterId": 4,
    "id": 13703,
    "isSupplemental": false,
    "worldBloomChapterType": "game_character"
  },
  {
    "aggregateAt": 1753786799000,
    "chapterEndAt": 1753787399000,
    "chapterNo": 4,
    "chapterStartAt": 1753527600000,
    "eventId": 137,
    "gameCharacterId": 1,
    "id": 13704,
    "isSupplemental": false,
    "worldBloomChapterType": "game_character"
  },
  {
    "aggregateAt": 1755601199000,
    "chapterEndAt": 1755601799000,
    "chapterNo": 1,
    "chapterStartAt": 1755428400000,
    "eventId": 140,
    "gameCharacterId": 24,
    "id": 14001,
    "isSupplemental": false,
    "worldBloomChapterType": "game_character"
  },
  {
    "aggregateAt": 1755773999000,
    "chapterEndAt": 1755774599000,
    "chapterNo": 2,
    "chapterStartAt": 1755601200000,
    "eventId": 140,
    "gameCharacterId": 22,
    "id": 14002,
    "isSupplemental": false,
    "worldBloomChapterType": "game_character"
  },
  {
    "aggregateAt": 1755946799000,
    "chapterEndAt": 1755947399000,
    "chapterNo": 3,
    "chapterStartAt": 1755774000000,
    "eventId": 140,
    "gameCharacterId": 25,
    "id": 14003,
    "isSupplemental": false,
    "worldBloomChapterType": "game_character"
  },
  {
    "aggregateAt": 1756119599000,
    "chapterEndAt": 1756120199000,
    "chapterNo": 4,
    "chapterStartAt": 1755946800000,
    "eventId": 140,
    "gameCharacterId": 23,
    "id": 14004,
    "isSupplemental": false,
    "worldBloomChapterType": "game_character"
  },
  {
    "aggregateAt": 1756292399000,
    "chapterEndAt": 1756292999000,
    "chapterNo": 5,
    "chapterStartAt": 1756119600000,
    "eventId": 140,
    "gameCharacterId": 26,
    "id": 14005,
    "isSupplemental": false,
    "worldBloomChapterType": "game_character"
  },
  {
    "aggregateAt": 1756465199000,
    "chapterEndAt": 1756465799000,
    "chapterNo": 6,
    "chapterStartAt": 1756292400000,
    "eventId": 140,
    "gameCharacterId": 21,
    "id": 14006,
    "isSupplemental": false,
    "worldBloomChapterType": "game_character"
  },
  {
    "aggregateAt": 1775991599000,
    "chapterEndAt": 1775992199000,
    "chapterNo": 1,
    "chapterStartAt": 1775732400000,
    "eventId": 163,
    "gameCharacterId": 12,
    "id": 16301,
    "isSupplemental": false,
    "worldBloomChapterType": "game_character"
  },
  {
    "aggregateAt": 1776250799000,
    "chapterEndAt": 1776251399000,
    "chapterNo": 2,
    "chapterStartAt": 1775991600000,
    "eventId": 163,
    "gameCharacterId": 11,
    "id": 16302,
    "isSupplemental": false,
    "worldBloomChapterType": "game_character"
  },
  {
    "aggregateAt": 1776509999000,
    "chapterEndAt": 1776510599000,
    "chapterNo": 3,
    "chapterStartAt": 1776250800000,
    "eventId": 163,
    "gameCharacterId": 9,
    "id": 16303,
    "isSupplemental": false,
    "worldBloomChapterType": "game_character"
  },
  {
    "aggregateAt": 1776769199000,
    "chapterEndAt": 1776769799000,
    "chapterNo": 4,
    "chapterStartAt": 1776510000000,
    "eventId": 163,
    "gameCharacterId": 10,
    "id": 16304,
    "isSupplemental": false,
    "worldBloomChapterType": "game_character"
  },
  {
    "aggregateAt": 1778583599000,
    "chapterEndAt": 1778584199000,
    "chapterNo": 1,
    "chapterStartAt": 1778324400000,
    "eventId": 167,
    "gameCharacterId": 16,
    "id": 16701,
    "isSupplemental": false,
    "worldBloomChapterType": "game_character"
  },
  {
    "aggregateAt": 1778842799000,
    "chapterEndAt": 1778843399000,
    "chapterNo": 2,
    "chapterStartAt": 1778583600000,
    "eventId": 167,
    "gameCharacterId": 13,
    "id": 16702,
    "isSupplemental": false,
    "worldBloomChapterType": "game_character"
  },
  {
    "aggregateAt": 1779101999000,
    "chapterEndAt": 1779102599000,
    "chapterNo": 3,
    "chapterStartAt": 1778842800000,
    "eventId": 167,
    "gameCharacterId": 15,
    "id": 16703,
    "isSupplemental": false,
    "worldBloomChapterType": "game_character"
  },
  {
    "aggregateAt": 1779361199000,
    "chapterEndAt": 1779361799000,
    "chapterNo": 4,
    "chapterStartAt": 1779102000000,
    "eventId": 167,
    "gameCharacterId": 14,
    "id": 16704,
    "isSupplemental": false,
    "worldBloomChapterType": "game_character"
  },
  {
    "aggregateAt": 1781261999000,
    "chapterEndAt": 1781262599000,
    "chapterNo": 1,
    "chapterStartAt": 1781002800000,
    "eventId": 170,
    "gameCharacterId": 17,
    "id": 17001,
    "isSupplemental": false,
    "worldBloomChapterType": "game_character"
  },
  {
    "aggregateAt": 1781521199000,
    "chapterEndAt": 1781521799000,
    "chapterNo": 2,
    "chapterStartAt": 1781262000000,
    "eventId": 170,
    "gameCharacterId": 19,
    "id": 17002,
    "isSupplemental": false,
    "worldBloomChapterType": "game_character"
  },
  {
    "aggregateAt": 1781780399000,
    "chapterEndAt": 1781780999000,
    "chapterNo": 3,
    "chapterStartAt": 1781521200000,
    "eventId": 170,
    "gameCharacterId": 20,
    "id": 17003,
    "isSupplemental": false,
    "worldBloomChapterType": "game_character"
  },
  {
    "aggregateAt": 1782039599000,
    "chapterEndAt": 1782040199000,
    "chapterNo": 4,
    "chapterStartAt": 1781780400000,
    "eventId": 170,
    "gameCharacterId": 18,
    "id": 17004,
    "isSupplemental": false,
    "worldBloomChapterType": "game_character"
  },
  {
    "aggregateAt": 1782471599000,
    "chapterEndAt": 1782472199000,
    "chapterNo": 1,
    "chapterStartAt": 1782212400000,
    "eventId": 171,
    "gameCharacterId": 4,
    "id": 17101,
    "isSupplemental": false,
    "worldBloomChapterType": "game_character"
  },
  {
    "aggregateAt": 1782730799000,
    "chapterEndAt": 1782731399000,
    "chapterNo": 2,
    "chapterStartAt": 1782471600000,
    "eventId": 171,
    "gameCharacterId": 2,
    "id": 17102,
    "isSupplemental": false,
    "worldBloomChapterType": "game_character"
  },
  {
    "aggregateAt": 1782989999000,
    "chapterEndAt": 1782990599000,
    "chapterNo": 3,
    "chapterStartAt": 1782730800000,
    "eventId": 171,
    "gameCharacterId": 3,
    "id": 17103,
    "isSupplemental": false,
    "worldBloomChapterType": "game_character"
  },
  {
    "aggregateAt": 1783249199000,
    "chapterEndAt": 1783249799000,
    "chapterNo": 4,
    "chapterStartAt": 1782990000000,
    "eventId": 171,
    "gameCharacterId": 1,
    "id": 17104,
    "isSupplemental": false,
    "worldBloomChapterType": "game_character"
  },
  {
    "aggregateAt": 1786445999000,
    "chapterEndAt": 1786446599000,
    "chapterNo": 1,
    "chapterStartAt": 1786186800000,
    "eventId": 176,
    "gameCharacterId": 5,
    "id": 17601,
    "isSupplemental": false,
    "worldBloomChapterType": "game_character"
  },
  {
    "aggregateAt": 1786705199000,
    "chapterEndAt": 1786705799000,
    "chapterNo": 2,
    "chapterStartAt": 1786446000000,
    "eventId": 176,
    "gameCharacterId": 6,
    "id": 17602,
    "isSupplemental": false,
    "worldBloomChapterType": "game_character"
  },
  {
    "aggregateAt": 1786964399000,
    "chapterEndAt": 1786964999000,
    "chapterNo": 3,
    "chapterStartAt": 1786705200000,
    "eventId": 176,
    "gameCharacterId": 7,
    "id": 17603,
    "isSupplemental": false,
    "worldBloomChapterType": "game_character"
  },
  {
    "aggregateAt": 1787223599000,
    "chapterEndAt": 1787224199000,
    "chapterNo": 4,
    "chapterStartAt": 1786964400000,
    "eventId": 176,
    "gameCharacterId": 8,
    "id": 17604,
    "isSupplemental": false,
    "worldBloomChapterType": "game_character"
  },
  {
    "aggregateAt": 1788865199000,
    "chapterEndAt": 1788865799000,
    "chapterNo": 1,
    "chapterStartAt": 1788692400000,
    "eventId": 179,
    "gameCharacterId": 23,
    "id": 17901,
    "isSupplemental": false,
    "worldBloomChapterType": "game_character"
  },
  {
    "aggregateAt": 1789037999000,
    "chapterEndAt": 1789038599000,
    "chapterNo": 2,
    "chapterStartAt": 1788865200000,
    "eventId": 179,
    "gameCharacterId": 21,
    "id": 17902,
    "isSupplemental": false,
    "worldBloomChapterType": "game_character"
  },
  {
    "aggregateAt": 1789210799000,
    "chapterEndAt": 1789211399000,
    "chapterNo": 3,
    "chapterStartAt": 1789038000000,
    "eventId": 179,
    "gameCharacterId": 24,
    "id": 17903,
    "isSupplemental": false,
    "worldBloomChapterType": "game_character"
  },
  {
    "aggregateAt": 1789383599000,
    "chapterEndAt": 1789384199000,
    "chapterNo": 4,
    "chapterStartAt": 1789210800000,
    "eventId": 179,
    "gameCharacterId": 25,
    "id": 17904,
    "isSupplemental": false,
    "worldBloomChapterType": "game_character"
  },
  {
    "aggregateAt": 1789556399000,
    "chapterEndAt": 1789556999000,
    "chapterNo": 5,
    "chapterStartAt": 1789383600000,
    "eventId": 179,
    "gameCharacterId": 26,
    "id": 17905,
    "isSupplemental": false,
    "worldBloomChapterType": "game_character"
  },
  {
    "aggregateAt": 1789729199000,
    "chapterEndAt": 1789729799000,
    "chapterNo": 6,
    "chapterStartAt": 1789556400000,
    "eventId": 179,
    "gameCharacterId": 22,
    "id": 17906,
    "isSupplemental": false,
    "worldBloomChapterType": "game_character"
  },
  {
    "aggregateAt": 1790593199000,
    "chapterEndAt": 1790593799000,
    "chapterNo": 1,
    "chapterStartAt": 1790334000000,
    "eventId": 180,
    "id": 18001,
    "isSupplemental": false,
    "worldBloomChapterType": "finale"
  }
]